audio_metadata/__about__.py
audio_metadata/__init__.py
audio_metadata/api.py
audio_metadata/exceptions.py
audio_metadata/formats/__init__.py
audio_metadata/formats/flac.py
audio_metadata/formats/id3v1.py
audio_metadata/formats/id3v2.py
audio_metadata/formats/id3v2frames.py
audio_metadata/formats/mp3.py
audio_metadata/formats/ogg.py
audio_metadata/formats/oggopus.py
audio_metadata/formats/oggvorbis.py
audio_metadata/formats/tables.py
audio_metadata/formats/vorbiscomments.py
audio_metadata/formats/wave.py
audio_metadata/models.py
audio_metadata/utils.py
audio_metadata-0.11.0.dist-info/LICENSE
audio_metadata-0.11.0.dist-info/WHEEL
audio_metadata-0.11.0.dist-info/METADATA
audio_metadata-0.11.0.dist-info/RECORD
